[
    {
        "id": "001",
        "nombre": "Cheescake Frutos Rojos",
        "desc": "Disfruta del rico sabor de un cheescake con el sabor de los mejores frutos rojos seleccionados, arandanos, fresas y frambuesas.",
        "img": "https://res.cloudinary.com/dninjpxlv/image/upload/v1664666511/pasteler%C3%ADa/cheescake-frutos-rojos_o64fdg.jpg",
        "precio": 20000,
        "stock":5,
        "categoria":"Heladas"
    },
    {
        "id": "002",
        "nombre": "Cheescake Fresa",
        "desc": "Un delicioso sabor del mejor cheescake de fresas con una textura cremosa y estilo tradicional.",
        "img": "https://res.cloudinary.com/dninjpxlv/image/upload/v1664667137/pasteler%C3%ADa/IMG1_x1v89i.jpg",
        "precio": 15000,
        "stock":6,
        "categoria":"Heladas"
    },
    {
        "id": "003",
        "nombre": "Torta glaseada de chocolate",
        "desc": "La mejor forma de degustar una rica torta chocolate con cobertura glaseada sabor a Choco Nutella.",
        "img": "https://res.cloudinary.com/dninjpxlv/image/upload/v1664667420/pasteler%C3%ADa/IMG3_kygdfl.jpg",
        "precio": 18000,
        "stock":10,
        "categoria":"Bizcocho"
    },
    {
        "id": "004",
        "nombre": "Torta Kit Kat",
        "desc": "Para complacer y darte un delicioso antojo, tenemos una torta rellena de chocolate, nutella y galletas al mejor estilo Kit Kat.",
        "img": "https://res.cloudinary.com/dninjpxlv/image/upload/v1664666579/pasteler%C3%ADa/IMG4_plizhl.jpg",
        "precio": 22000,
        "stock":15,
        "categoria":"Panqueque"
    },
    {
        "id": "005",
        "nombre": "Cheescake Maracuya",
        "desc": "Para disfrutar un sabor unico y en familia, te ofrecemos la mejor combinación, lo tradicional de un cheescake, con el exquisito sabor de la maracuya.",
        "img": "https://res.cloudinary.com/dninjpxlv/image/upload/v1664666596/pasteler%C3%ADa/IMG6_vmh0pw.jpg",
        "precio": 18000,
        "stock":8,
        "categoria":"Heladas"
    },
    {
        "id": "006",
        "nombre": "Torta Charlotte",
        "desc": "La mejor torta al estilo selva negra, con deliciosa crema batida, fresas y un delicisoso sabor a chocolate",
        "img": "https://res.cloudinary.com/dninjpxlv/image/upload/v1664667016/pasteler%C3%ADa/selva-negra_jxrj1d.webp",
        "precio": 25000,
        "stock":15,
        "categoria":"Panqueque"
    },
    {
        "id": "007",
        "nombre": "Torta Melanie",
        "desc": "Esta deliciosa torta de suave bizcocho y rellena con rico manjar y chispas, no dudaras en probarla.",
        "img": "https://res.cloudinary.com/dninjpxlv/image/upload/v1664666693/pasteler%C3%ADa/torta-manjar_mtlrrh.jpg",
        "precio": 20000,
        "stock":15,
        "categoria":"MilHoja"
    },
    {
        "id": "008",
        "nombre": "Torta Rubí",
        "desc": "Si prefieres un sabor diferente, para ti la rica y deliciosa torta Red Velvet, la mejor para ocaciones unicas.",
        "img": "https://res.cloudinary.com/dninjpxlv/image/upload/v1664667327/pasteler%C3%ADa/tortaredvelve_zrztpz.webp",
        "precio": 28000,
        "stock":15,
        "categoria":"Panqueque"
    },
    {
        "id": "009",
        "nombre": "Torta Marquesa",
        "desc": "Este rico e inigualable sabor de una marquesa de chocolate, rellena de chocolate y manjar siempre la disfrutaras.",
        "img": "https://res.cloudinary.com/dninjpxlv/image/upload/v1664666701/pasteler%C3%ADa/tortachocolate1_ejxonh.webp",
        "precio": 23000,
        "stock":15,
        "categoria":"MilHoja"

    },
    {
        "id": "010",
        "nombre": "Torta Elinor",
        "desc": "Cuando de sorprender se trata, esta exquisita y elegante torta con cubierta de glaseado real y rellena de choconutella, es la mejor opción al momento de complacer paladares.",
        "img": "https://res.cloudinary.com/dninjpxlv/image/upload/v1664666695/pasteler%C3%ADa/tortaglaseada-chocolate_rclbox.jpg",
        "precio": 30000,
        "stock":10,
        "categoria":"Bizcocho"
    },
    {
        "id": "011",
        "nombre": "Cheescake Tradicional",
        "desc": "Prueba este exquisito cheescake con cubierta de glaseado de frambuesa, es la mejor opción al momento de compartir en familia.",
        "img": "https://res.cloudinary.com/dninjpxlv/image/upload/v1664667169/pasteler%C3%ADa/cheescak-individual_fscldz.jpg",
        "precio": 20000,
        "stock":12,
        "categoria":"Heladas"
    },
    {
        "id": "012",
        "nombre": "Tarta Pastel de Arandanos",
        "desc": "Esta rica e inigualable tarta de arandanos, rellena de chocolate es la excusa perfecta para cuando de antojos de trata.",
        "img": "https://res.cloudinary.com/dninjpxlv/image/upload/v1664666949/pasteler%C3%ADa/tarta-pastel-arandanos_pbrfoq.jpg",
        "precio": 25000,
        "stock":8,
        "categoria":"Bizcocho"
    },
    {
        "id": "013",
        "nombre": "Torta Magnific",
        "desc": "Esta deliciosa torta de suave bizcocho, rellena con chocolate semi-amargo y chispas de chocolate, doble sabor exquisita y elegante, cubierta de glaseado real es la mejor opción para complacer paladares.",
        "img": "https://res.cloudinary.com/dninjpxlv/image/upload/v1664666499/pasteler%C3%ADa/BANNER_ncymuq.jpg",
        "precio": 30000,
        "stock":11,
        "categoria":"Bizcocho"
    },
    {
        "id": "014",
        "nombre": "Panqueque Orange",
        "desc": "Este rico y sencillo panqueque de naranja, es la mejor opción al momento de compartir y disfrutar un momento en familia.",
        "img": "https://res.cloudinary.com/dninjpxlv/image/upload/v1676335616/pasteler%C3%ADa/panqueque_naranja_hfv6rz.jpg",
        "precio": 18000,
        "stock":10,
        "categoria":"Panqueque"
    },
    {
        "id": "015",
        "nombre": "Torta July",
        "desc": "Cuando de sorprender se trata, esta exquisita torta con cubierta de glaseado de frutas tropicales, no dudarás en probarla.",
        "img": "https://res.cloudinary.com/dninjpxlv/image/upload/v1676336242/pasteler%C3%ADa/torta_de_frutas_obgjap.webp",
        "precio": 22000,
        "stock":12,
        "categoria":"MilHoja"
    },
    {
        "id": "016",
        "nombre": "Torta Jane",
        "desc": "Cuando de destacar se trata, esta exquisita torta con cubierta de glaseado y rellena de choconutella, es la opción correcta para sorprender.",
        "img": "https://res.cloudinary.com/dninjpxlv/image/upload/v1676336201/pasteler%C3%ADa/Degustando-Milhojas_qikubk.png",
        "precio": 30000,
        "stock":15,
        "categoria":"MilHoja"
    }

]